{
  "version": 1,
  "author": "Uri Shaked",
  "editor": "wokwi",
  "parts": [
    { "type": "board-esp32-devkit-c-v4", "id": "esp", "top": 19.2, "left": -62.36, "attrs": {} },
    { "type": "wokwi-led", "id": "led1", "top": -3.6, "left": 138.2, "attrs": { "color": "red" } },
    {
      "type": "wokwi-resistor",
      "id": "r1",
      "top": 138.35,
      "left": 105.6,
      "attrs": { "value": "220" }
    },
    {
      "type": "wokwi-led",
      "id": "led2",
      "top": -3.6,
      "left": 234.2,
      "attrs": { "color": "green" }
    },
    {
      "type": "wokwi-resistor",
      "id": "r2",
      "top": 109.55,
      "left": 201.6,
      "attrs": { "value": "1000" }
    }
  ],
  "connections": [
    [ "esp:TX", "$serialMonitor:RX", "", [] ],
    [ "esp:RX", "$serialMonitor:TX", "", [] ],
    [ "led1:C", "esp:GND.2", "black", [ "v0" ] ],
    [ "led1:A", "r1:2", "green", [ "v0" ] ],
    [ "r1:1", "esp:17", "green", [ "v0" ] ],
    [ "led2:C", "esp:GND.2", "green", [ "v0" ] ],
    [ "led2:A", "r2:2", "green", [ "v0" ] ],
    [ "r2:1", "esp:4", "green", [ "v0" ] ]
  ],
  "dependencies": {}
}